bullfrog.py
setup.py
bullfrog.egg-info/PKG-INFO
bullfrog.egg-info/SOURCES.txt
bullfrog.egg-info/dependency_links.txt
bullfrog.egg-info/entry_points.txt
bullfrog.egg-info/requires.txt
bullfrog.egg-info/top_level.txt