Metadata-Version: 1.0
Name: bullfrog
Version: 0.0.1
Summary: It eats everything
Home-page: UNKNOWN
Author: Zach Smith
Author-email: zachmsmith@gmail.com
License: UNKNOWN
Platform: UNKNOWN
